oslo_middleware/__init__.py
oslo_middleware/_i18n.py
oslo_middleware/base.py
oslo_middleware/basic_auth.py
oslo_middleware/catch_errors.py
oslo_middleware/correlation_id.py
oslo_middleware/cors.py
oslo_middleware/debug.py
oslo_middleware/exceptions.py
oslo_middleware/http_proxy_to_wsgi.py
oslo_middleware/opts.py
oslo_middleware/request_id.py
oslo_middleware/sizelimit.py
oslo_middleware/stats.py
oslo_middleware/version.py
oslo_middleware/healthcheck/__init__.py
oslo_middleware/healthcheck/__main__.py
oslo_middleware/healthcheck/disable_by_file.py
oslo_middleware/healthcheck/enable_by_files.py
oslo_middleware/healthcheck/opts.py
oslo_middleware/healthcheck/pluginbase.py
oslo_middleware/locale/en_GB/LC_MESSAGES/oslo_middleware.po
oslo_middleware/tests/__init__.py
oslo_middleware/tests/test_auth_basic.py
oslo_middleware/tests/test_base.py
oslo_middleware/tests/test_catch_errors.py
oslo_middleware/tests/test_correlation_id.py
oslo_middleware/tests/test_cors.py
oslo_middleware/tests/test_entry_points.py
oslo_middleware/tests/test_healthcheck.py
oslo_middleware/tests/test_http_proxy_to_wsgi.py
oslo_middleware/tests/test_opts.py
oslo_middleware/tests/test_request_id.py
oslo_middleware/tests/test_sizelimit.py
oslo_middleware/tests/test_stats.py
oslo_middleware-6.6.0.dist-info/AUTHORS
oslo_middleware-6.6.0.dist-info/LICENSE
oslo_middleware-6.6.0.dist-info/METADATA
oslo_middleware-6.6.0.dist-info/WHEEL
oslo_middleware-6.6.0.dist-info/entry_points.txt
oslo_middleware-6.6.0.dist-info/pbr.json
oslo_middleware-6.6.0.dist-info/top_level.txt
oslo_middleware-6.6.0.dist-info/RECORD
