Metadata-Version: 2.1
Name: oslo.middleware
Version: 6.6.0
Summary: Oslo Middleware library
Home-page: https://docs.openstack.org/oslo.middleware/latest/
Author: OpenStack
Author-email: openstack-discuss@lists.openstack.org
Classifier: Environment :: OpenStack
Classifier: Intended Audience :: Information Technology
Classifier: Intended Audience :: System Administrators
Classifier: License :: OSI Approved :: Apache Software License
Classifier: Operating System :: POSIX :: Linux
Classifier: Programming Language :: Python
Classifier: Programming Language :: Python :: 3
Classifier: Programming Language :: Python :: 3.9
Classifier: Programming Language :: Python :: 3.10
Classifier: Programming Language :: Python :: 3.11
Classifier: Programming Language :: Python :: 3.12
Classifier: Programming Language :: Python :: 3 :: Only
Classifier: Programming Language :: Python :: Implementation :: CPython
Requires-Python: >=3.9
License-File: LICENSE
Requires-Dist: bcrypt>=3.1.3
Requires-Dist: debtcollector>=1.2.0
Requires-Dist: Jinja2>=2.10
Requires-Dist: oslo.config>=5.2.0
Requires-Dist: oslo.context>=2.19.2
Requires-Dist: oslo.i18n>=3.15.3
Requires-Dist: oslo.utils>=3.33.0
Requires-Dist: pbr>=2.0.0
Requires-Dist: statsd>=3.2.1
Requires-Dist: stevedore>=1.20.0
Requires-Dist: typing-extensions>=4.11.0
Requires-Dist: WebOb>=1.8.0
